{
  "mission": {
    "title": "探索、引导、实施",
    "subtitle": "我们的使命",
    "info": "我们致力于为学生提供实质性、高效性、趣味性的优质课程资源，通过线上教育推动企业的推广和发展,相信在不久的将来，行业风口之势必会如星火燎原般席卷中国教育市场，我们有能力也有信息乘上这个时代的风帆，扬帆起航。",
    "img": "/img/about1.png"
  },
  "featute": {
    "title": "多样运营模式",
    "tabs": [
      { "title": "多方位的在线教育", "img": "img/关于-小圆图1.png" },
      { "title": "线下优质课程", "img": "img/关于-小圆图2.png" },
      { "title": "面向大赛的实质化提升", "img": "img/关于-小圆图3.png" }
    ]
  },
  "intro": {
    "title": "核心观念",
    "info": "提供线下培训能更好的了解学员的情况，从而能够因材施教，并不断完善课程内容获得更多的用户认可， 形成口碑。编程学习社区是提供给学员的重要交流平台，通过学员之间的交流，巩固学习成果。官方也会参与到社区中， 解答疑难问题，帮助学员，一方面不仅能够让学生真实的感受到编程的用处，另一方面通过参加或组织编程比赛，让口碑也获得提升。",
    "img": "/img/about2.png"
  }
}
